README.md
setup.py
TOPSIS_Stuti_101853033.egg-info/PKG-INFO
TOPSIS_Stuti_101853033.egg-info/SOURCES.txt
TOPSIS_Stuti_101853033.egg-info/dependency_links.txt
TOPSIS_Stuti_101853033.egg-info/entry_points.txt
TOPSIS_Stuti_101853033.egg-info/requires.txt
TOPSIS_Stuti_101853033.egg-info/top_level.txt
src/topsis.py